src/__init__.py
src/string_to_bool.py
string_to_bool/__init__.py
string_to_bool/string_to_bool.py
string_to_bool-0.0.2.dist-info/LICENSE
string_to_bool-0.0.2.dist-info/METADATA
string_to_bool-0.0.2.dist-info/WHEEL
string_to_bool-0.0.2.dist-info/top_level.txt
string_to_bool-0.0.2.dist-info/RECORD
